canonicalwebteam/__init__.py
canonicalwebteam/image_template/__init__.py
canonicalwebteam/templates/image_template.html
canonicalwebteam_image_template-1.9.0.dist-info/METADATA
canonicalwebteam_image_template-1.9.0.dist-info/WHEEL
canonicalwebteam_image_template-1.9.0.dist-info/top_level.txt
canonicalwebteam_image_template-1.9.0.dist-info/RECORD
