Metadata-Version: 2.4
Name: canonicalwebteam.image-template
Version: 1.9.0
Summary: Generate <img> markup block for an image.
Home-page: https://github.com/canonical-web-and-design/canonicalwebteam.image-template
Author: Canonical webteam
Author-email: webteam@canonical.com
Requires-Dist: jinja2>=2
Dynamic: author
Dynamic: author-email
Dynamic: description
Dynamic: description-content-type
Dynamic: home-page
Dynamic: requires-dist
Dynamic: summary
